ktoolkit/__init__.py
ktoolkit-0.0.2.dist-info/METADATA
ktoolkit-0.0.2.dist-info/WHEEL
ktoolkit-0.0.2.dist-info/top_level.txt
ktoolkit-0.0.2.dist-info/RECORD
